<?xml version="1.0"?>
<font type="bitmap">

	<Texture index="0" filename="optima18Black.png" hasAlpha="true" />

	<c c="!" r="0, 0, 5, 18" />
	<c c="&quot;" r="5, 0, 12, 9" />
	<c c="#" r="12, 0, 27, 18" />
	<c c="$" r="27, 0, 39, 21" />
	<c c="%" r="39, 0, 60, 19" />
	<c c="&amp;" r="60, 0, 77, 18" />
	<c c="'" r="77, 0, 80, 9" />
	<c c="(" r="80, 0, 86, 22" />
	<c c=")" r="86, 0, 92, 22" />
	<c c="*" r="92, 0, 101, 11" />
	<c c="+" r="101, 0, 114, 18" />
	<c c="," r="114, 0, 120, 22" />
	<c c="-" r="120, 0, 127, 12" />
	<c c="." r="127, 0, 132, 18" />
	<c c="/" r="132, 0, 141, 18" />
	<c c="0" r="141, 0, 154, 18" />
	<c c="1" r="154, 0, 164, 18" />
	<c c="2" r="164, 0, 177, 18" />
	<c c="3" r="177, 0, 189, 18" />
	<c c="4" r="189, 0, 202, 18" />
	<c c="5" r="202, 0, 214, 18" />
	<c c="6" r="214, 0, 227, 18" />
	<c c="7" r="227, 0, 239, 18" />
	<c c="8" r="239, 0, 252, 18" />
	<c c="9" r="0, 22, 13, 40" />
	<c c=":" r="13, 22, 18, 40" />
	<c c=";" r="18, 22, 24, 45" />
	<c c="&lt;" r="24, 22, 38, 41" />
	<c c="=" r="38, 22, 52, 37" />
	<c c="&gt;" r="52, 22, 66, 41" />
	<c c="?" r="66, 22, 74, 40" />
	<c c="@" r="74, 22, 93, 40" />
	<c c="A" r="93, 22, 110, 40" />
	<c c="B" r="110, 22, 123, 40" />
	<c c="C" r="123, 22, 140, 40" />
	<c c="D" r="140, 22, 157, 40" />
	<c c="E" r="157, 22, 167, 40" />
	<c c="F" r="167, 22, 177, 40" />
	<c c="G" r="177, 22, 194, 40" />
	<c c="H" r="194, 22, 210, 40" />
	<c c="I" r="210, 22, 215, 40" />
	<c c="J" r="215, 22, 222, 44" />
	<c c="K" r="222, 22, 236, 40" />
	<c c="L" r="236, 22, 247, 40" />
	<c c="M" r="0, 45, 22, 63" />
	<c c="N" r="22, 45, 38, 63" />
	<c c="O" r="38, 45, 58, 63" />
	<c c="P" r="58, 45, 70, 63" />
	<c c="Q" r="70, 45, 90, 68" />
	<c c="R" r="90, 45, 104, 63" />
	<c c="S" r="104, 45, 116, 63" />
	<c c="T" r="116, 45, 131, 63" />
	<c c="U" r="131, 45, 147, 63" />
	<c c="V" r="147, 45, 164, 63" />
	<c c="W" r="164, 45, 189, 63" />
	<c c="X" r="189, 45, 205, 63" />
	<c c="Y" r="205, 45, 221, 63" />
	<c c="Z" r="221, 45, 237, 63" />
	<c c="[" r="237, 45, 243, 66" />
	<c c="\" r="243, 45, 252, 63" />
	<c c="]" r="0, 68, 6, 89" />
	<c c="^" r="6, 68, 17, 80" />
	<c c="_" r="17, 68, 30, 89" />
	<c c="`" r="30, 68, 38, 73" />
	<c c="a" r="38, 68, 50, 86" />
	<c c="b" r="50, 68, 63, 86" />
	<c c="c" r="63, 68, 75, 86" />
	<c c="d" r="75, 68, 88, 86" />
	<c c="e" r="88, 68, 101, 86" />
	<c c="f" r="101, 68, 110, 86" />
	<c c="g" r="110, 68, 123, 92" />
	<c c="h" r="123, 68, 135, 86" />
	<c c="i" r="135, 68, 139, 86" />
	<c c="j" r="139, 68, 145, 92" />
	<c c="k" r="145, 68, 157, 86" />
	<c c="l" r="157, 68, 161, 86" />
	<c c="m" r="161, 68, 180, 86" />
	<c c="n" r="180, 68, 192, 86" />
	<c c="o" r="192, 68, 206, 86" />
	<c c="p" r="206, 68, 220, 92" />
	<c c="q" r="220, 68, 233, 92" />
	<c c="r" r="233, 68, 241, 86" />
	<c c="s" r="241, 68, 251, 86" />
	<c c="t" r="0, 92, 9, 110" />
	<c c="u" r="9, 92, 21, 110" />
	<c c="v" r="21, 92, 34, 110" />
	<c c="w" r="34, 92, 54, 110" />
	<c c="x" r="54, 92, 67, 110" />
	<c c="y" r="67, 92, 80, 116" />
	<c c="z" r="80, 92, 93, 110" />
	<c c="{" r="93, 92, 103, 113" />
	<c c="|" r="103, 92, 107, 116" />
	<c c="}" r="107, 92, 116, 113" />
	<c c="~" r="116, 92, 131, 105" />
</font>